aiowpi/__init__.py
aiowpi/client.py
aiowpi/decorators.py
aiowpi/error.py
aiowpi-0.1.8.dist-info/LICENSE
aiowpi-0.1.8.dist-info/METADATA
aiowpi-0.1.8.dist-info/WHEEL
aiowpi-0.1.8.dist-info/top_level.txt
aiowpi-0.1.8.dist-info/RECORD
