Metadata-Version: 2.2
Name: aiowpi
Version: 0.1.8
Summary: Async Python client for the World of Warships API.
Author-email: INTMAX <INT_MAX@hotmail.com>
License: MIT
Project-URL: homepage, https://github.com/Int-0X7FFFFFFF/aiowpi
Project-URL: repository, https://github.com/Int-0X7FFFFFFF/aiowpi
Keywords: async,wows,api,client,aiolimiter
Classifier: License :: OSI Approved :: MIT License
Classifier: Programming Language :: Python :: 3 :: Only
Classifier: Programming Language :: Python :: 3.8
Classifier: Programming Language :: Python :: 3.9
Classifier: Programming Language :: Python :: 3.10
Classifier: Programming Language :: Python :: 3.11
Classifier: Programming Language :: Python :: 3.12
Classifier: Programming Language :: Python :: Implementation :: CPython
Classifier: Topic :: Software Development :: Libraries :: Python Modules
Requires-Python: >=3.8
License-File: LICENSE
Requires-Dist: aiohttp
Requires-Dist: aiolimiter
